{
    "monsters": [
        {
            "id": "02_01_rabbit",
            "name": "兔子",
            "description": "一隻毛色灰白的野兔，看起來很機警。雖然不具威脅性，但動作敏捷。",
            "icon": "hare",
            "level": 1,
            "health": 15,
            "attack": 2,
            "defense": 1,
            "experience": 5,
            "lootTableId": "06_01_loot_rabbit",
            "spawnScenes": ["03_04_mountain", "03_06_forest_path"]
        },
        {
            "id": "02_02_chicken",
            "name": "雞",
            "description": "一隻在路邊覓食的野雞，完全沒有戒心。是最容易對付的生物。",
            "icon": "bird",
            "level": 1,
            "health": 10,
            "attack": 1,
            "defense": 0,
            "experience": 3,
            "lootTableId": "06_02_loot_chicken",
            "spawnScenes": ["03_04_mountain"]
        },
        {
            "id": "02_03_wild_boar",
            "name": "野豬",
            "description": "一頭體型壯碩的野豬，正在用獠牙翻掘泥土。受到驚嚇時會變得極具攻擊性。",
            "icon": "pawprint.fill",
            "level": 3,
            "health": 40,
            "attack": 8,
            "defense": 4,
            "experience": 15,
            "lootTableId": null,
            "spawnScenes": ["03_05_deep_mountain", "03_06_forest_path"]
        },
        {
            "id": "02_04_wolf",
            "name": "灰狼",
            "description": "一匹目光銳利的灰狼，正低伏著身體注視著四周。牠的動作迅捷而致命。",
            "icon": "dog.fill",
            "level": 4,
            "health": 35,
            "attack": 10,
            "defense": 3,
            "experience": 20,
            "lootTableId": null,
            "spawnScenes": ["03_05_deep_mountain"]
        }
    ]
}
